{
  "schemaVersion": 1,
  "id": "utpa",
  "version": "${version}",
  "name": "UltimateTpaMod",
  "description": "Mod combines the tpa, homes and back functionalaties for a server.",
  "authors": ["AyushGerra"],
  "contact": {
    "homepage": "https://fabricmc.net/",
    "sources": "https://github.com/FabricMC/fabric-example-mod"
  },
  "license": "CC0-1.0",
  "environment": "*",
  "entrypoints": {
    "main": ["com.example.UltimateTpaMod"]
  },
  "mixins": ["utpa.mixins.json"],
  "depends": {
    "fabricloader": ">=0.19.2",
    "minecraft": ">=26.1",
    "java": ">=25",
    "fabric-api": "*"
  },
  "suggests": {
    "another-mod": "*"
  }
}
